{
	"$schema": "https://schema.management.azure.com/schemas/2015-01-01/deploymentParameters.json#",
	"contentVersion": "1.0.0.0",
	"parameters": {
		"factoryName": {
			"value": "demoDF50s"
		},
		"AzureDataLakeStorage_accountKey": {
			"value": ""
		},
		"SqlServer1_connectionString": {
			"value": ""
		},
		"SqlServer2_connectionString": {
			"value": ""
		},
		"AzureDataLakeStorage_properties_typeProperties_url": {
			"value": "https://storagetest50s.dfs.core.windows.net/"
		},
		"AzureDatabricks_properties_typeProperties_existingClusterId": {
			"value": "0215-145711-n9ke1668"
		},
		"AzureKeyVault1_properties_typeProperties_baseUrl": {
			"value": "https://demoVault50.vault.azure.net/"
		}
	}
}